{
  "TranslationProperties": {
    "Name": "server.items.pickle_flag.name"
  },
  "MaxStack": 16,
  "Icon": "Icons/ItemsGenerated/pickle_flag.png",
  "Categories": [
    "Blocks.Deco"
  ],
  "PlayerAnimationsId": "Block",
  "Set": "Deco_Flag",
  "BlockType": {
    "Material": "Solid",
    "DrawType": "Model",
    "Group": "Wood",
    "Opacity": "Transparent",
    "BlockSoundSetId": "Cloth",
    "BlockParticleSetId": "Cloth",
    "CustomModel": "Models/pickle_flagpole.bbmodel",
    "CustomModelTexture": [
      {
        "Texture": "BlockTextures/flagpole.png",
        "Weight": 1
      }
    ],
    "CustomModelScale": 1,
    "HitboxType": "Block_Torch",
    "VariantRotation": "Wall"
  },
  "Gathering": {
    "Tool": "Any",
    "Drops": [
      {
        "ItemId": "pickle_flag",
        "Quantity": 1
      }
    ]
  }
}
